LinuxMinglingxingYuShellJiaobenJiaochengFix1/README.md
LinuxMinglingxingYuShellJiaobenJiaochengFix1/__init__.py
LinuxMinglingxingYuShellJiaobenJiaochengFix1/__main__.py
LinuxMinglingxingYuShellJiaobenJiaochengFix1/file.epub
LinuxMinglingxingYuShellJiaobenJiaochengFix1/index.html
LinuxMinglingxingYuShellJiaobenJiaochengFix1/css/__init__.py
LinuxMinglingxingYuShellJiaobenJiaochengFix1/css/annotations.css
LinuxMinglingxingYuShellJiaobenJiaochengFix1/css/main.css
LinuxMinglingxingYuShellJiaobenJiaochengFix1/css/normalize.css
LinuxMinglingxingYuShellJiaobenJiaochengFix1/css/popup.css
LinuxMinglingxingYuShellJiaobenJiaochengFix1/font/__init__.py
LinuxMinglingxingYuShellJiaobenJiaochengFix1/font/fontello.eot
LinuxMinglingxingYuShellJiaobenJiaochengFix1/font/fontello.svg
LinuxMinglingxingYuShellJiaobenJiaochengFix1/font/fontello.ttf
LinuxMinglingxingYuShellJiaobenJiaochengFix1/font/fontello.woff
LinuxMinglingxingYuShellJiaobenJiaochengFix1/img/__init__.py
LinuxMinglingxingYuShellJiaobenJiaochengFix1/img/annotator-glyph-sprite.png
LinuxMinglingxingYuShellJiaobenJiaochengFix1/img/annotator-icon-sprite.png
LinuxMinglingxingYuShellJiaobenJiaochengFix1/img/apple-touch-icon.png
LinuxMinglingxingYuShellJiaobenJiaochengFix1/img/cancelfullscreen.png
LinuxMinglingxingYuShellJiaobenJiaochengFix1/img/close.png
LinuxMinglingxingYuShellJiaobenJiaochengFix1/img/fullscreen.png
LinuxMinglingxingYuShellJiaobenJiaochengFix1/img/loader.gif
LinuxMinglingxingYuShellJiaobenJiaochengFix1/img/menu-icon.png
LinuxMinglingxingYuShellJiaobenJiaochengFix1/img/save.png
LinuxMinglingxingYuShellJiaobenJiaochengFix1/img/saved.png
LinuxMinglingxingYuShellJiaobenJiaochengFix1/img/settings-s.png
LinuxMinglingxingYuShellJiaobenJiaochengFix1/img/settings.png
LinuxMinglingxingYuShellJiaobenJiaochengFix1/img/star.png
LinuxMinglingxingYuShellJiaobenJiaochengFix1/js/__init__.py
LinuxMinglingxingYuShellJiaobenJiaochengFix1/js/epub.js
LinuxMinglingxingYuShellJiaobenJiaochengFix1/js/epub.min.js
linux_minglingxing_yu_shell_jiaoben_jiaocheng_fix1-2025.3.25.1.dist-info/METADATA
linux_minglingxing_yu_shell_jiaoben_jiaocheng_fix1-2025.3.25.1.dist-info/WHEEL
linux_minglingxing_yu_shell_jiaoben_jiaocheng_fix1-2025.3.25.1.dist-info/entry_points.txt
linux_minglingxing_yu_shell_jiaoben_jiaocheng_fix1-2025.3.25.1.dist-info/top_level.txt
linux_minglingxing_yu_shell_jiaoben_jiaocheng_fix1-2025.3.25.1.dist-info/RECORD
